airflow_module/__init__.py
airflow_module/my_test.py
airflow_module-0.1.2.dist-info/METADATA
airflow_module-0.1.2.dist-info/WHEEL
airflow_module-0.1.2.dist-info/top_level.txt
airflow_module-0.1.2.dist-info/RECORD
